tcpcan/__init__.py
tcpcan-0.0.2.dist-info/LICENSE
tcpcan-0.0.2.dist-info/METADATA
tcpcan-0.0.2.dist-info/WHEEL
tcpcan-0.0.2.dist-info/entry_points.txt
tcpcan-0.0.2.dist-info/top_level.txt
tcpcan-0.0.2.dist-info/RECORD
