Metadata-Version: 2.1
Name: tcpcan
Version: 0.0.2
Summary: A socketCAN on TCP client/server
Home-page: https://github.com/simontegelid/tcpcan
Author: Simon Tegelid
Author-email: simon.tegelid@niradynamics.se
License: UNKNOWN
Project-URL: Bug Tracker, https://github.com/simontegelid/tcpcan/issues
Platform: UNKNOWN
Classifier: Programming Language :: Python :: 3
Classifier: License :: OSI Approved :: Apache Software License
Classifier: Operating System :: POSIX :: Linux
Requires-Python: >=3.3
